<?xml version="1.0" standalone="no"?>
<EasyView Name="DrGwListsListView" Description="sipadmin.rtg.drouting" Class="EasyView" Tab="" TemplateEngine="Smarty" Access="SIPAdmin.Administer_Modules" TemplateFile="view.tpl">
   <FormReferences>
   		<Reference Name="sipadmin.rtg.drouting.form.DrGwListsListForm"/>
   </FormReferences>
   <FormReferenceLibs>
   		<Reference Name="sipadmin.rtg.drouting.form.DrGwListsListForm"/>
   		<Reference Name="sipadmin.rtg.drouting.form.DrGwListsEditForm"/>
   		<Reference Name="sipadmin.rtg.drouting.form.DrGwListsCopyForm"/>
   		<Reference Name="sipadmin.rtg.drouting.form.DrGwListsNewForm"/>
   		<Reference Name="sipadmin.rtg.drouting.form.DrGwListsDetailForm"/>
   </FormReferenceLibs>    
</EasyView>
