<?xml version="1.0" encoding="UTF-8"?>
<EasyForm Name="MohqueuesCopyForm" Class="EasyForm" FormType="Edit" jsClass="jbForm" Title="Copy Mohqueues" Description="" BizDataObj="sipadmin.msc.mohqueues.do.MohqueuesDO" TemplateEngine="Smarty" TemplateFile="detail.tpl" EventName="" MessageFile="">
    <DataPanel>
        <Element Name="fld_Id" Class="Hidden" FieldName="Id" Label="Id" AllowURLParam="Y"/>	
		<Element Name="fld_name" Class="InputText" FieldName="name" Label="Name"  AllowURLParam="N" CssClass="input_text" CssErrorClass="input_text_error" CssFocusClass="input_text_focus"/>
		<Element Name="fld_uri" Class="InputText" FieldName="uri" Label="Uri"  AllowURLParam="N" CssClass="input_text" CssErrorClass="input_text_error" CssFocusClass="input_text_focus"/>
		<Element Name="fld_mohdir" Class="InputText" FieldName="mohdir" Label="Mohdir"  AllowURLParam="N" CssClass="input_text" CssErrorClass="input_text_error" CssFocusClass="input_text_focus"/>
		<Element Name="fld_mohfile" Class="InputText" FieldName="mohfile" Label="Mohfile"  AllowURLParam="N" CssClass="input_text" CssErrorClass="input_text_error" CssFocusClass="input_text_focus"/>
		<Element Name="fld_debug" Class="InputText" FieldName="debug" Label="Debug"  AllowURLParam="N" CssClass="input_text" CssErrorClass="input_text_error" CssFocusClass="input_text_focus"/>
    </DataPanel>
    <ActionPanel>
        <Element Name="btn_save" Class="Button" Text="Save" CssClass="button_gray_m">
            <EventHandler Name="save_onclick" EventLogMsg="" Event="onclick" Function="InsertRecord()" RedirectPage="form=sipadmin.msc.mohqueues.form.MohqueuesDetailForm&amp;fld:Id={@sipadmin.msc.mohqueues.do.MohqueuesDO:Field[Id].Value}"  ShortcutKey="Ctrl+Enter" ContextMenu="Save" />
        </Element>
        <Element Name="btn_cancel" Class="Button" Text="Cancel" CssClass="button_gray_m">
            <EventHandler Name="cancel_onclick" Event="onclick" Function="SwitchForm(sipadmin.msc.mohqueues.form.MohqueuesListForm)"  ShortcutKey="Escape" ContextMenu="Cancel"/>
        </Element>
    </ActionPanel> 
    <NavPanel>
    </NavPanel> 
    <SearchPanel>
    </SearchPanel>
</EasyForm>
